textlog/__init__.py
textlog/log.py
textlog-0.0.1.1.dist-info/LICENSE
textlog-0.0.1.1.dist-info/METADATA
textlog-0.0.1.1.dist-info/WHEEL
textlog-0.0.1.1.dist-info/top_level.txt
textlog-0.0.1.1.dist-info/RECORD
