Metadata-Version: 2.1
Name: textlog
Version: 0.0.1.1
Summary: Simple python text log
Home-page: https://github.com/Sotaneum/textlog
Author: LEE DONG GUN
Author-email: gnyotnu39@gmail.com
License: MIT
Platform: UNKNOWN
Classifier: License :: OSI Approved :: MIT License
